NodeJsDiaoshiZhinan/README.md
NodeJsDiaoshiZhinan/__init__.py
NodeJsDiaoshiZhinan/__main__.py
NodeJsDiaoshiZhinan/file.epub
NodeJsDiaoshiZhinan/index.html
NodeJsDiaoshiZhinan/css/__init__.py
NodeJsDiaoshiZhinan/css/annotations.css
NodeJsDiaoshiZhinan/css/main.css
NodeJsDiaoshiZhinan/css/normalize.css
NodeJsDiaoshiZhinan/css/popup.css
NodeJsDiaoshiZhinan/font/__init__.py
NodeJsDiaoshiZhinan/font/fontello.eot
NodeJsDiaoshiZhinan/font/fontello.svg
NodeJsDiaoshiZhinan/font/fontello.ttf
NodeJsDiaoshiZhinan/font/fontello.woff
NodeJsDiaoshiZhinan/img/__init__.py
NodeJsDiaoshiZhinan/img/annotator-glyph-sprite.png
NodeJsDiaoshiZhinan/img/annotator-icon-sprite.png
NodeJsDiaoshiZhinan/img/apple-touch-icon.png
NodeJsDiaoshiZhinan/img/cancelfullscreen.png
NodeJsDiaoshiZhinan/img/close.png
NodeJsDiaoshiZhinan/img/fullscreen.png
NodeJsDiaoshiZhinan/img/loader.gif
NodeJsDiaoshiZhinan/img/menu-icon.png
NodeJsDiaoshiZhinan/img/save.png
NodeJsDiaoshiZhinan/img/saved.png
NodeJsDiaoshiZhinan/img/settings-s.png
NodeJsDiaoshiZhinan/img/settings.png
NodeJsDiaoshiZhinan/img/star.png
NodeJsDiaoshiZhinan/js/__init__.py
NodeJsDiaoshiZhinan/js/epub.js
NodeJsDiaoshiZhinan/js/epub.min.js
NodeJsDiaoshiZhinan/js/epub.min.map
NodeJsDiaoshiZhinan/js/hooks.min.js
NodeJsDiaoshiZhinan/js/hooks.min.map
NodeJsDiaoshiZhinan/js/reader.js
NodeJsDiaoshiZhinan/js/reader.js.map
NodeJsDiaoshiZhinan/js/reader.min.js
NodeJsDiaoshiZhinan/js/reader.min.map
NodeJsDiaoshiZhinan/js/hooks/__init__.py
NodeJsDiaoshiZhinan/js/hooks/extensions/__init__.py
NodeJsDiaoshiZhinan/js/hooks/extensions/highlight.js
NodeJsDiaoshiZhinan/js/libs/__init__.py
NodeJsDiaoshiZhinan/js/libs/jquery.min.js
NodeJsDiaoshiZhinan/js/libs/localforage.min.js
NodeJsDiaoshiZhinan/js/libs/screenfull.js
NodeJsDiaoshiZhinan/js/libs/screenfull.min.js
NodeJsDiaoshiZhinan/js/libs/zip.min.js
NodeJsDiaoshiZhinan/js/plugins/__init__.py
NodeJsDiaoshiZhinan/js/plugins/hypothesis.js
NodeJsDiaoshiZhinan/js/plugins/search.js
node_js_diaoshi_zhinan-2024.3.3.0.dist-info/METADATA
node_js_diaoshi_zhinan-2024.3.3.0.dist-info/WHEEL
node_js_diaoshi_zhinan-2024.3.3.0.dist-info/entry_points.txt
node_js_diaoshi_zhinan-2024.3.3.0.dist-info/top_level.txt
node_js_diaoshi_zhinan-2024.3.3.0.dist-info/RECORD
